{
    "providers" :
    [
        {
            "name"              : "emdeon",
            "datafeed_id"       : "10",
            "datatype"          : "medicalclaims",
            "record_field"      : "claim_id",
            "fill_rate"         : true,
            "key_stats"         : true,
            "top_values"        : true,
            "longitudinality"   : true,
            "year_over_year"    : true,
            "epi_calcs"         : true,
            "earliest_date"     : "2013-01-01"
        },
        {
            "name"              : "emdeon",
            "datafeed_id"       : "11",
            "datatype"          : "pharmacyclaims",
            "record_field"      : "claim_id",
            "fill_rate"         : true,
            "key_stats"         : true,
            "top_values"        : true,
            "longitudinality"   : true,
            "year_over_year"    : true,
            "epi_calcs"         : true,
            "earliest_date"     : "2012-01-01"
        },
        {
            "name"              : "caris",
            "datafeed_id"       : "14",
            "datatype"          : "labtests",
            "record_field"      : "record_id",
            "fill_rate"         : true,
            "key_stats"         : true,
            "top_values"        : true,
            "longitudinality"   : false,
            "year_over_year"    : false,
            "epi_calcs"         : true,
            "earliest_date"     : "2010-01-01"
        },
        {
            "name"              : "ability",
            "datafeed_id"       : "15",
            "datatype"          : "medicalclaims",
            "record_field"      : "claim_id",
            "fill_rate"         : true,
            "key_stats"         : true,
            "top_values"        : true,
            "longitudinality"   : true,
            "year_over_year"    : true,
            "epi_calcs"         : true,
            "earliest_date"     : "2014-01-01"
        },
        {
            "name"              : "express_scripts",
            "datafeed_id"       : "16",
            "datatype"          : "pharmacyclaims",
            "record_field"      : "claim_id",
            "fill_rate"         : true,
            "key_stats"         : true,
            "top_values"        : true,
            "longitudinality"   : true,
            "year_over_year"    : true,
            "epi_calcs"         : true,
            "earliest_date"     : "2009-08-01"
        },
        {
            "name"              : "quest",
            "datafeed_id"       : "18",
            "datatype"          : "labtests",
            "record_field"      : "claim_id",
            "fill_rate"         : true,
            "key_stats"         : true,
            "top_values"        : true,
            "longitudinality"   : true,
            "year_over_year"    : true,
            "epi_calcs"         : true,
            "earliest_date"     : "2014-08-01"
        },
        {
            "name"              : "aurora_diagnostics",
            "datafeed_id"       : "85",
            "datatype"          : "labtests",
            "record_field"      : "claim_id",
            "fill_rate"         : true,
            "key_stats"         : true,
            "top_values"        : true,
            "longitudinality"   : true,
            "year_over_year"    : true,
            "epi_calcs"         : true,
            "earliest_date"     : "2013-01-01"
        },
        {
            "name"              : "guardant_health",
            "datafeed_id"       : "58",
            "datatype"          : "labtests",
            "fill_rate"         : true,
            "key_stats"         : true,
            "top_values"        : true,
            "longitudinality"   : false,
            "year_over_year"    : false,
            "epi_calcs"         : true,
            "earliest_date"     : "2015-05-01"
        },
        {
            "name"              : "genoa",
            "datafeed_id"       : "21",
            "datatype"          : "pharmacyclaims",
            "record_field"      : "claim_id",
            "fill_rate"         : true,
            "key_stats"         : true,
            "top_values"        : true,
            "longitudinality"   : true,
            "year_over_year"    : true,
            "epi_calcs"         : true,
            "earliest_date"     : "2011-01-01"
        },
        {
            "name"              : "practice_insight",
            "datafeed_id"       : "22",
            "datatype"          : "medicalclaims",
            "record_field"      : "claim_id",
            "fill_rate"         : true,
            "key_stats"         : true,
            "top_values"        : true,
            "longitudinality"   : true,
            "year_over_year"    : true,
            "epi_calcs"         : true,
            "earliest_date"     : "2012-01-01"
        },
        {
            "name"              : "xifin",
            "datafeed_id"       : "55",
            "datatype"          : "medicalclaims",
            "record_field"      : "claim_id",
            "fill_rate"         : true,
            "key_stats"         : true,
            "top_values"        : true,
            "longitudinality"   : true,
            "year_over_year"    : true,
            "epi_calcs"         : true,
            "earliest_date"     : "2014-01-01"
        },
        {
            "name"              : "allscripts",
            "datafeed_id"       : "25",
            "datatype"          : "emr",
            "models"            : [
              {
                "datatype"        : "emr_clin_obsn",
                "fill_rate"       : true,
                "top_values"      : true
              }, {
                "datatype"        : "emr_medctn",
                "fill_rate"       : true,
                "top_values"      : true
              }, {
                "datatype"        : "emr_enc",
                "fill_rate"       : true,
                "top_values"      : true
              }, {
                "datatype"        : "emr_prov_ord",
                "fill_rate"       : true,
                "top_values"      : true
              }, {
                "datatype"        : "emr_lab_test",
                "fill_rate"       : true,
                "top_values"      : true
              }, {
                "datatype"        : "emr_proc",
                "fill_rate"       : true,
                "top_values"      : true
              }, {
                "datatype"        : "emr_diag",
                "fill_rate"       : true,
                "top_values"      : true
              }
            ],
            "epi_calcs"         : true,
            "key_stats"         : true,
            "longitudinality"   : true,
            "year_over_year"    : true,
            "earliest_date"     : "2014-01-01",
            "index_null_dates"  : true
        },
        {
            "name"              : "allscripts",
            "datafeed_id"       : "26",
            "datatype"          : "medicalclaims",
            "record_field"      : "claim_id",
            "fill_rate"         : true,
            "key_stats"         : true,
            "top_values"        : true,
            "longitudinality"   : true,
            "year_over_year"    : true,
            "epi_calcs"         : true,
            "earliest_date"     : "2015-01-01"
        },
        {
            "name"              : "obituarydata",
            "datafeed_id"       : "27",
            "datatype"          : "events",
            "fill_rate"         : false,
            "key_stats"         : true,
            "top_values"        : false,
            "longitudinality"   : false,
            "year_over_year"    : false,
            "epi_calcs"         : true,
            "earliest_date"     : "1994-12-01"
        },
        {
            "name"              : "navicure",
            "datafeed_id"       : "24",
            "datatype"          : "medicalclaims",
            "record_field"      : "claim_id",
            "fill_rate"         : true,
            "key_stats"         : true,
            "top_values"        : true,
            "longitudinality"   : true,
            "year_over_year"    : true,
            "epi_calcs"         : true,
            "earliest_date"     : "2015-01-01"
        },
        {
            "name"              : "labcorp",
            "datafeed_id"       : "46",
            "datatype"          : "labtests",
            "fill_rate"         : true,
            "key_stats"         : true,
            "top_values"        : true,
            "longitudinality"   : false,
            "year_over_year"    : true,
            "epi_calcs"         : true,
            "earliest_date"     : "2017-04-01"
        },
        {
            "name"              : "genomind",
            "datafeed_id"       : "76",
            "datatype"          : "labtests",
            "fill_rate"         : true,
            "key_stats"         : true,
            "top_values"        : true,
            "longitudinality"   : false,
            "year_over_year"    : false,
            "epi_calcs"         : true,
            "earliest_date"     : "1900-01-01",
            "index_all_dates"   : true,
            "index_null_dates"  : true,
            "custom_schema"     : "sample",
            "custom_table"      : "genomind_normalized"
        },
        {
            "name"              : "ambry",
            "datafeed_id"       : "43",
            "datatype"          : "labtests",
            "fill_rate"         : true,
            "key_stats"         : true,
            "top_values"        : true,
            "longitudinality"   : false,
            "year_over_year"    : false,
            "epi_calcs"         : true,
            "earliest_date"     : "2016-06-01"
        },
        {
            "name"              : "neogenomics",
            "datafeed_id"       : "32",
            "datatype"          : "labtests",
            "record_field"      : "claim_id",
            "fill_rate"         : true,
            "key_stats"         : true,
            "top_values"        : true,
            "longitudinality"   : false,
            "year_over_year"    : false,
            "epi_calcs"         : true,
            "earliest_date"     : "2014-01-01",
            "index_all_dates"   : true
        },
        {
            "name"              : "mckesson",
            "datafeed_id"       : "33",
            "datatype"          : "pharmacyclaims",
            "record_field"      : "claim_id",
            "fill_rate"         : true,
            "key_stats"         : true,
            "top_values"        : true,
            "longitudinality"   : true,
            "year_over_year"    : true,
            "epi_calcs"         : true,
            "earliest_date"     : "2011-01-01"
        },
        {
            "name"              : "mckesson_macro_helix",
            "datafeed_id"       : "51",
            "datatype"          : "pharmacyclaims",
            "record_field"      : "claim_id",
            "fill_rate"         : true,
            "key_stats"         : true,
            "top_values"        : true,
            "longitudinality"   : true,
            "year_over_year"    : true,
            "epi_calcs"         : true,
            "earliest_date"     : "2016-01-01"
        },
        {
            "name"              : "cardinal_vitalpath",
            "datafeed_id"       : "30",
            "datatype"          : "pharmacyclaims",
            "fill_rate"         : true,
            "key_stats"         : true,
            "top_values"        : true,
            "longitudinality"   : true,
            "year_over_year"    : true,
            "epi_calcs"         : true,
            "earliest_date"     : "2012-02-01"
        },
        {
            "name"              : "cardinal_pds",
            "datafeed_id"       : "39",
            "datatype"          : "pharmacyclaims",
            "record_field"      : "claim_id",
            "fill_rate"         : true,
            "key_stats"         : true,
            "top_values"        : true,
            "longitudinality"   : true,
            "year_over_year"    : true,
            "epi_calcs"         : true,
            "earliest_date"     : "2011-02-01"
        },
        {
            "name"              : "mckesson_res",
            "datafeed_id"       : "36",
            "datatype"          : "pharmacyclaims",
            "fill_rate"         : true,
            "key_stats"         : true,
            "top_values"        : true,
            "longitudinality"   : true,
            "year_over_year"    : true,
            "epi_calcs"         : true,
            "earliest_date"     : "2011-01-01"
        },
        {
            "name"              : "nextgen",
            "datafeed_id"       : "35",
            "datatype"          : "emr",
            "models"            : [
              {
                "datatype"        : "emr_clin_obsn",
                "fill_rate"       : true,
                "top_values"      : true
              }, {
                "datatype"        : "emr_medctn",
                "fill_rate"       : true,
                "top_values"      : true
              }, {
                "datatype"        : "emr_prov_ord",
                "fill_rate"       : true,
                "top_values"      : true
              }, {
                "datatype"        : "emr_enc",
                "fill_rate"       : true,
                "top_values"      : true
              }, {
                "datatype"        : "emr_lab_test",
                "fill_rate"       : true,
                "top_values"      : true
              }, {
                "datatype"        : "emr_proc",
                "fill_rate"       : true,
                "top_values"      : true
              }, {
                "datatype"        : "emr_diag",
                "fill_rate"       : true,
                "top_values"      : true
              }
            ],
            "epi_calcs"         : true,
            "key_stats"         : true,
            "longitudinality"   : true,
            "year_over_year"    : true,
            "earliest_date"     : "2003-01-01"
        },
        {
            "name"              : "amazingcharts",
            "datafeed_id"       : "5",
            "datatype"          : "emr",
            "models"            : [
              {
                "datatype"        : "emr_enc",
                "fill_rate"       : true,
                "top_values"      : true
              }, {
                "datatype"        : "emr_clin_obsn",
                "fill_rate"       : true,
                "top_values"      : true
              }, {
                "datatype"        : "emr_medctn",
                "fill_rate"       : true,
                "top_values"      : true
              }, {
                "datatype"        : "emr_lab_test",
                "fill_rate"       : true,
                "top_values"      : true
              }, {
                "datatype"        : "emr_proc",
                "fill_rate"       : true,
                "top_values"      : true
              }, {
                "datatype"        : "emr_diag",
                "fill_rate"       : true,
                "top_values"      : true
              }
            ],
            "epi_calcs"         : true,
            "key_stats"         : true,
            "longitudinality"   : true,
            "year_over_year"    : true,
            "earliest_date"     : "2015-10-01",
            "index_all_dates"   : false,
            "index_null_dates"  : true
        },
        {
            "name"              : "healthjump",
            "datafeed_id"       : "47",
            "datatype"          : "emr",
            "models"            : [
              {
                "datatype"        : "emr_medctn",
                "fill_rate"       : true,
                "top_values"      : true
              }, {
                "datatype"        : "emr_proc",
                "fill_rate"       : true,
                "top_values"      : true
              }, {
                "datatype"        : "emr_diag",
                "fill_rate"       : true,
                "top_values"      : true
              }, {
                "datatype"        : "emr_lab_test",
                "fill_rate"       : true,
                "top_values"      : true
              }
            ],
            "epi_calcs"         : true,
            "key_stats"         : true,
            "longitudinality"   : true,
            "year_over_year"    : true,
            "earliest_date"     : "2008-01-01",
            "index_all_dates"   : true,
            "index_null_dates"  : true
        },
        {
            "name"              : "cardinal_rcm",
            "datafeed_id"       : "29",
            "datatype"          : "medicalclaims",
            "record_field"      : "claim_id",
            "fill_rate"         : true,
            "key_stats"         : true,
            "top_values"        : true,
            "longitudinality"   : true,
            "year_over_year"    : true,
            "epi_calcs"         : true,
            "index_all_dates"   : true,
            "earliest_date"     : "2012-01-01"
        },
        {
            "name"              : "mindbody",
            "datafeed_id"       : "38",
            "datatype"          : "events",
            "earliest_date"     : "2015-04-01",
            "fill_rate"         : false,
            "key_stats"         : true,
            "top_values"        : false,
            "longitudinality"   : true,
            "year_over_year"    : true,
            "epi_calcs"         : false
        },
        {
            "name"              : "alliance",
            "datafeed_id"       : "56",
            "datatype"          : "events",
            "fill_rate"         : false,
            "key_stats"         : true,
            "top_values"        : false,
            "longitudinality"   : true,
            "year_over_year"    : true,
            "epi_calcs"         : true,
            "earliest_date"     : "2015-04-01",
            "index_all_dates"   : true,
            "index_null_dates"  : true
        },
        {
            "name"              : "diplomat",
            "datafeed_id"       : "34",
            "datatype"          : "pharmacyclaims",
            "fill_rate"         : true,
            "key_stats"         : true,
            "top_values"        : true,
            "longitudinality"   : true,
            "year_over_year"    : true,
            "epi_calcs"         : true,
            "earliest_date"     : "2015-01-01"
        },
        {
            "name"              : "pdx",
            "datafeed_id"       : "65",
            "datatype"          : "pharmacyclaims",
            "fill_rate"         : true,
            "key_stats"         : true,
            "top_values"        : true,
            "longitudinality"   : true,
            "year_over_year"    : true,
            "epi_calcs"         : true,
            "earliest_date"     : "2015-01-01"
        },
        {
            "name"              : "apothecary_by_design",
            "datafeed_id"       : "45",
            "datatype"          : "pharmacyclaims",
            "fill_rate"         : true,
            "key_stats"         : true,
            "top_values"        : true,
            "longitudinality"   : true,
            "year_over_year"    : true,
            "epi_calcs"         : true,
            "earliest_date"     : "2017-01-01"
        },
        {
            "name"              : "epsilon",
            "datafeed_id"       : "42",
            "datatype"          : "events",
            "fill_rate"         : true,
            "key_stats"         : true,
            "top_values"        : false,
            "longitudinality"   : true,
            "year_over_year"    : true,
            "epi_calcs"         : true,
            "earliest_date"     : "2015-09-01"
        },
        {
            "name"              : "acxiom",
            "datafeed_id"       : "50",
            "datatype"          : "events",
            "fill_rate"         : true,
            "key_stats"         : true,
            "top_values"        : false,
            "longitudinality"   : true,
            "year_over_year"    : true,
            "epi_calcs"         : true,
            "earliest_date"     : "2017-01-01",
            "index_all_dates"   : true,
            "index_null_dates"  : true
        },
        {
            "name"              : "cardinal_raintree_emr",
            "datafeed_id"       : "40",
            "datatype"          : "emr",
            "models"            : [
              {
                "datatype"        : "emr_clin_obsn",
                "fill_rate"       : true,
                "top_values"      : true
              }, {
                "datatype"        : "emr_medctn",
                "fill_rate"       : true,
                "top_values"      : true
              }, {
                "datatype"        : "emr_prov_ord",
                "fill_rate"       : true,
                "top_values"      : true
              }, {
                "datatype"        : "emr_lab_test",
                "fill_rate"       : true,
                "top_values"      : true
              }, {
                "datatype"        : "emr_enc",
                "fill_rate"       : true,
                "top_values"      : true
              }, {
                "datatype"        : "emr_proc",
                "fill_rate"       : true,
                "top_values"      : true
              }, {
                "datatype"        : "emr_diag",
                "fill_rate"       : true,
                "top_values"      : true
              }
            ],
          "epi_calcs"         : true,
          "key_stats"         : true,
          "longitudinality"   : true,
          "year_over_year"    : true,
          "earliest_date"     : "2011-02-01",
          "index_all_dates"   : true,
          "index_null_dates"  : true
        },
        {
            "name"              : "transmed",
            "datafeed_id"       : "54",
            "datatype"          : "emr",
            "models"            : [
              {
                "datatype"        : "emr_clin_obsn",
                "fill_rate"       : true,
                "top_values"      : true
              }, {
                "datatype"        : "emr_lab_test",
                "fill_rate"       : true,
                "top_values"      : true
              }, {
                "datatype"        : "emr_proc",
                "fill_rate"       : true,
                "top_values"      : true
              }, {
                "datatype"        : "emr_diag",
                "fill_rate"       : true,
                "top_values"      : true
              }
            ],
          "epi_calcs"         : true,
          "key_stats"         : true,
          "longitudinality"   : true,
          "year_over_year"    : true,
          "earliest_date"     : "2017-01-01",
          "index_all_dates"   : true,
          "index_null_dates"  : true
        },
        {
            "name"              : "cardinal_tsi",
            "datafeed_id"       : "31",
            "datatype"          : "emr",
            "models"            : [
              {
                "datatype"        : "emr_medctn",
                "fill_rate"       : true,
                "top_values"      : true
              }, {
                "datatype"        : "emr_diag",
                "fill_rate"       : true,
                "top_values"      : true
              }
            ],
          "epi_calcs"         : true,
          "key_stats"         : true,
          "longitudinality"   : true,
          "year_over_year"    : true,
          "earliest_date"     : "2012-01-01",
          "index_all_dates"   : true,
          "index_null_dates"  : true
        },
        {
            "name"              : "8451",
            "datafeed_id"       : "86",
            "datatype"          : "pharmacyclaims",
            "fill_rate"         : true,
            "key_stats"         : true,
            "top_values"        : true,
            "longitudinality"   : true,
            "year_over_year"    : true,
            "epi_calcs"         : true,
            "earliest_date"     : "2014-01-01"
        }
    ]
}
